{
  "project_info": {
    "project_number": "679645096836",
    "project_id": "sella-386306",
    "storage_bucket": "sella-386306.appspot.com"
  },
  "client": [
    {
      "client_info": {
        "mobilesdk_app_id": "1:679645096836:android:0a15d5bb6b77b89b960bd1",
        "android_client_info": {
          "package_name": "com.vshalbhati_294.sella"
        }
      },
      "oauth_client": [
        {
          "client_id": "679645096836-lh64j503kh070k25jvcn94eu4n4bi08b.apps.googleusercontent.com",
          "client_type": 1,
          "android_info": {
            "package_name": "com.vshalbhati_294.sella",
            "certificate_hash": "87a5804f5b993042a38c38db0fddd32e57f489de"
          }
        },
        {
          "client_id": "679645096836-775l66pkib93nmrlgf8thqpokgmig79d.apps.googleusercontent.com",
          "client_type": 3
        }
      ],
      "api_key": [
        {
          "current_key": "AIzaSyCRoCXlnl4nBhh70OJpPDGpXcad7tRe2Bk"
        }
      ],
      "services": {
        "appinvite_service": {
          "other_platform_oauth_client": [
            {
              "client_id": "679645096836-775l66pkib93nmrlgf8thqpokgmig79d.apps.googleusercontent.com",
              "client_type": 3
            },
            {
              "client_id": "679645096836-8ek87f9v7047a8itbnctqmphvekkq4eu.apps.googleusercontent.com",
              "client_type": 2,
              "ios_info": {
                "bundle_id": "com.vshalbhati_294.sella"
              }
            }
          ]
        }
      }
    }
  ],
  "configuration_version": "1"
}